CHANGES.rst
MANIFEST.in
README.rst
TODO.rst
setup.py
src/ao/__init__.py
src/ao.shorturl.egg-info/PKG-INFO
src/ao.shorturl.egg-info/SOURCES.txt
src/ao.shorturl.egg-info/dependency_links.txt
src/ao.shorturl.egg-info/namespace_packages.txt
src/ao.shorturl.egg-info/requires.txt
src/ao.shorturl.egg-info/top_level.txt
src/ao.shorturl.egg-info/zip-safe
src/ao/shorturl/__init__.py
src/ao/shorturl/appengine.py
src/ao/shorturl/appengine.rst
src/ao/shorturl/django.rst
src/ao/shorturl/interfaces.py
src/ao/shorturl/shorturl.rst
src/ao/shorturl/tests.py
src/ao/shorturl/templatetags/__init__.py
src/ao/shorturl/templatetags/shorturl.py